camino_ai/__init__.py
camino_ai/client.py
camino_ai/models.py
camino_ai/workflows.py
camino_ai_sdk-0.5.0.dist-info/METADATA
camino_ai_sdk-0.5.0.dist-info/WHEEL
camino_ai_sdk-0.5.0.dist-info/entry_points.txt
camino_ai_sdk-0.5.0.dist-info/RECORD
