Metadata-Version: 2.4
Name: camino-ai-sdk
Version: 0.5.0
Summary: Camino AI Python SDK for location intelligence and spatial reasoning
License: MIT
Keywords: camino,ai,geospatial,location,routing,sdk
Author: Camino AI
Author-email: support@getcamino.ai
Requires-Python: >=3.9,<4.0
Classifier: Development Status :: 4 - Beta
Classifier: Intended Audience :: Developers
Classifier: License :: OSI Approved :: MIT License
Classifier: Operating System :: OS Independent
Classifier: Programming Language :: Python :: 3
Classifier: Programming Language :: Python :: 3.9
Classifier: Programming Language :: Python :: 3.10
Classifier: Programming Language :: Python :: 3.11
Classifier: Programming Language :: Python :: 3.12
Classifier: Programming Language :: Python :: 3.13
Classifier: Programming Language :: Python :: 3.14
Classifier: Topic :: Scientific/Engineering :: GIS
Classifier: Topic :: Software Development :: Libraries :: Python Modules
Requires-Dist: eval-type-backport (>=0.2.0,<0.3.0) ; python_version < "3.10"
Requires-Dist: httpx (>=0.28.0,<0.29.0)
Requires-Dist: pydantic (>=2.0.0,<3.0.0)
Requires-Dist: typing-extensions (>=4.5.0,<5.0.0)
Project-URL: Documentation, https://docs.getcamino.ai
Project-URL: Homepage, https://github.com/camino-ai/camino-sdks
Project-URL: Repository, https://github.com/camino-ai/camino-sdks
